ezaero/__init__.py
ezaero/vlm/__init__.py
ezaero/vlm/plotting.py
ezaero/vlm/steady.py
ezaero-0.1.dev4.dist-info/LICENSE
ezaero-0.1.dev4.dist-info/METADATA
ezaero-0.1.dev4.dist-info/WHEEL
ezaero-0.1.dev4.dist-info/top_level.txt
ezaero-0.1.dev4.dist-info/RECORD
