Metadata-Version: 2.1
Name: ezaero
Version: 0.1.dev4
Summary: Aerodynamics in Python.
Home-page: https://github.com/partmor/ezaero
Author: Pedro Arturo Morales Maries
Author-email: part.morales@gmail.com
License: MIT
Download-URL: https://github.com/partmor/ezaero
Project-URL: Source, https://github.com/partmor/ezaero
Project-URL: Tracker, https://github.com/partmor/ezaero/issues
Keywords: aero,aerospace,engineering,aerodynamics,vlm
Platform: any
Classifier: Development Status :: 2 - Pre-Alpha
Classifier: Intended Audience :: Education
Classifier: Intended Audience :: Science/Research
Classifier: License :: OSI Approved :: MIT License
Classifier: Operating System :: OS Independent
Classifier: Programming Language :: Python
Classifier: Programming Language :: Python :: 3
Classifier: Programming Language :: Python :: 3.7
Classifier: Programming Language :: Python :: 3.8
Classifier: Programming Language :: Python :: Implementation :: CPython
Classifier: Topic :: Scientific/Engineering
Classifier: Topic :: Scientific/Engineering :: Physics
Requires-Python: <3.9,>=3.7
Requires-Dist: matplotlib (>=2.0)
Requires-Dist: numpy
Provides-Extra: dev
Requires-Dist: tox ; extra == 'dev'
Provides-Extra: docs
Requires-Dist: pillow ; extra == 'docs'
Requires-Dist: sphinx ; extra == 'docs'
Requires-Dist: sphinx-gallery ; extra == 'docs'
Requires-Dist: sphinx-rtd-theme ; extra == 'docs'
